{
  "ProductContexts": [
    {
      "IsStockLimit": true,
      "ProductId": 10001,
      "ProductType": 1,
      "ProductName": "保税仓：Merries花王婴儿纸尿裤L54片适用9-14kg ",
      "Stock": 201,
      "PresellCount": 0,
      "LeaveStoreDay": 0,
      "ImgUrl": "./images/156389_01_01.jpg",
      "ShowImgUrl": "http://img.boodoll.cn/Product/{0}/12792_01_01.jpg",
      "SaleState": true,
      "MarketPrice": 35.0000,
      "PromotionStock": 292,
      "PromotionUseStock": 0,
      "PromPrice": 1900,
      "PromPriceShow": 99.00
    },
    {
      "IsStockLimit": true,
      "ProductId": 10002,
      "ProductType": 1,
      "ProductName": "保税仓：moony尤妮佳婴幼儿纸尿裤M64片适用6-11kg ",
      "Stock": 29,
      "PresellCount": 0,
      "LeaveStoreDay": 0,
      "ImgUrl": "./images/156389_01_01.jpg",
      "ShowImgUrl": "http://img.boodoll.cn/pdt/img/a3/cef7cc17a7c1b29_{type}.jpg",
      "SaleState": true,
      "MarketPrice": 79.0000,
      "PromotionStock": 380,
      "PromotionUseStock": 0,
      "PromPrice": 3990,
      "PromPriceShow": 125.00
    },
    {
      "IsStockLimit": true,
      "ProductId": 10003,
      "ProductType": 1,
      "ProductName": "保税仓：Merries花王婴儿纸尿裤M42片适用6-11kg",
      "Stock": 197,
      "PresellCount": 0,
      "LeaveStoreDay": 0,
      "ImgUrl": "./images/156389_01_01.jpg",
      "ShowImgUrl": "http://img.boodoll.cn/Product/{0}/43756_01_01.jpg",
      "SaleState": true,
      "MarketPrice": 16.0000,
      "PromotionStock": 197,
      "PromotionUseStock": 0,
      "PromPrice": 790,
      "PromPriceShow": 78
    },
    {
      "IsStockLimit": true,
      "ProductId": 10004,
      "ProductType": 1,
      "ProductName": "花王婴儿纸尿裤L54片（新老包装交替）",
      "Stock": 70,
      "PresellCount": 0,
      "LeaveStoreDay": 0,
      "ImgUrl": "./images/156389_01_01.jpg",
      "ShowImgUrl": "./images",
      "SaleState": true,
      "MarketPrice": 15.0000,
      "PromotionStock": 70,
      "PromotionUseStock": 0,
      "PromPrice": 690,
      "PromPriceShow": 128.00
    }
  ],
  "pampers": [
    {
      "IsStockLimit": true,
      "ProductId": 10005,
      "ProductType": 1,
      "ProductName": "Huggies好奇铂金装倍柔亲肤透气纸尿裤NB84片（初生-5kg）",
      "ProductNamenext":"周年店庆",
      "Stock": 201,
      "PresellCount": 0,
      "LeaveStoreDay": 0,
      "ImgUrl": "./images/47c324e0c151d758_380X380.jpg",
      "ShowImgUrl": "http://img.boodoll.cn/Product/{0}/12792_01_01.jpg",
      "SaleState": true,
      "MarketPrice": 35.0000,
      "PromotionStock": 292,
      "PromotionUseStock": 0,
      "PromPrice": 1900,
      "PromPriceShow": 79.00
    },
    {
      "IsStockLimit": true,
      "ProductId": 10006,
      "ProductType": 1,
      "ProductName": "小白熊全棉透气防溢乳垫72+8片（颜色随机）",
      "ProductNamenext":"周年店庆",
      "Stock": 29,
      "PresellCount": 0,
      "LeaveStoreDay": 0,
      "ImgUrl": "./images/47c324e0c151d758_380X380.jpg",
      "ShowImgUrl": "http://img.boodoll.cn/pdt/img/a3/cef7cc17a7c1b29_{type}.jpg",
      "SaleState": true,
      "MarketPrice": 79.0000,
      "PromotionStock": 380,
      "PromotionUseStock": 0,
      "PromPrice": 3990,
      "PromPriceShow": 39.90
    },
    {
      "IsStockLimit": true,
      "ProductId": 10007,
      "ProductType": 1,
      "ProductName": "Moony婴儿纸尿裤M64片（新老包装交替）",
      "ProductNamenext":"周年店庆",
      "Stock": 197,
      "PresellCount": 0,
      "LeaveStoreDay": 0,
      "ImgUrl": "./images/47c324e0c151d758_380X380.jpg",
      "ShowImgUrl": "http://img.boodoll.cn/Product/{0}/43756_01_01.jpg",
      "SaleState": true,
      "MarketPrice": 16.0000,
      "PromotionStock": 197,
      "PromotionUseStock": 0,
      "PromPrice": 790,
      "PromPriceShow": 95.00
    },
    {
      "IsStockLimit": true,
      "ProductId": 10008,
      "ProductType": 1,
      "ProductName": "保税仓：Merries花王婴儿纸尿裤S82片适用4-8kg   ",
      "ProductNamenext":"周年店庆",
      "Stock": 70,
      "PresellCount": 0,
      "LeaveStoreDay": 0,
      "ImgUrl": "./images/47c324e0c151d758_380X380.jpg",
      "ShowImgUrl": "./images",
      "SaleState": true,
      "MarketPrice": 15.0000,
      "PromotionStock": 70,
      "PromotionUseStock": 0,
      "PromPrice": 690,
      "PromPriceShow": 79.00
    },
    {
      "IsStockLimit": true,
      "ProductId": 10009,
      "ProductType": 1,
      "ProductName": "贝惠谊14X全棉纯棉超柔六层纱布浴巾90*110cm白",
      "ProductNamenext":"周年店庆",
      "Stock": 201,
      "PresellCount": 0,
      "LeaveStoreDay": 0,
      "ImgUrl": "./images/47c324e0c151d758_380X380.jpg",
      "ShowImgUrl": "http://img.boodoll.cn/Product/{0}/12792_01_01.jpg",
      "SaleState": true,
      "MarketPrice": 35.0000,
      "PromotionStock": 292,
      "PromotionUseStock": 0,
      "PromPrice": 1900,
      "PromPriceShow": 79.00
    },
    {
      "IsStockLimit": true,
      "ProductId": 100010,
      "ProductType": 1,
      "ProductName": "贝亲宽口径玻璃奶瓶240ml（绿色）",
      "ProductNamenext":"周年店庆",
      "Stock": 29,
      "PresellCount": 0,
      "LeaveStoreDay": 0,
      "ImgUrl": "./images/47c324e0c151d758_380X380.jpg",
      "ShowImgUrl": "http://img.boodoll.cn/pdt/img/a3/cef7cc17a7c1b29_{type}.jpg",
      "SaleState": true,
      "MarketPrice": 79.0000,
      "PromotionStock": 380,
      "PromotionUseStock": 0,
      "PromPrice": 3990,
      "PromPriceShow": 29.00
    }
  ],
  "coon": [
    {
      "IsStockLimit": true,
      "ProductId": 100011,
      "ProductType": 1,
      "ProductName": "Huggies好奇铂金装倍柔亲肤透气纸尿裤NB84片（初生-5kg）",
      "ProductNamenext":"周年店庆",
      "Stock": 201,
      "PresellCount": 0,
      "LeaveStoreDay": 0,
      "ImgUrl": "./images/156629_01_01.jpg",
      "ShowImgUrl": "http://img.boodoll.cn/Product/{0}/12792_01_01.jpg",
      "SaleState": true,
      "MarketPrice": 35.0000,
      "PromotionStock": 292,
      "PromotionUseStock": 0,
      "PromPrice": 1900,
      "PromPriceShow": 79.00
    },
    {
      "IsStockLimit": true,
      "ProductId": 100012,
      "ProductType": 1,
      "ProductName": "小白熊全棉透气防溢乳垫72+8片（颜色随机）",
      "ProductNamenext":"周年店庆",
      "Stock": 29,
      "PresellCount": 0,
      "LeaveStoreDay": 0,
      "ImgUrl": "./images/156629_01_01.jpg",
      "ShowImgUrl": "http://img.boodoll.cn/pdt/img/a3/cef7cc17a7c1b29_{type}.jpg",
      "SaleState": true,
      "MarketPrice": 79.0000,
      "PromotionStock": 380,
      "PromotionUseStock": 0,
      "PromPrice": 3990,
      "PromPriceShow": 39.90
    },
    {
      "IsStockLimit": true,
      "ProductId": 100013,
      "ProductType": 1,
      "ProductName": "Moony婴儿纸尿裤M64片（新老包装交替）",
      "ProductNamenext":"周年店庆",
      "Stock": 197,
      "PresellCount": 0,
      "LeaveStoreDay": 0,
      "ImgUrl": "./images/156629_01_01.jpg",
      "ShowImgUrl": "http://img.boodoll.cn/Product/{0}/43756_01_01.jpg",
      "SaleState": true,
      "MarketPrice": 16.0000,
      "PromotionStock": 197,
      "PromotionUseStock": 0,
      "PromPrice": 790,
      "PromPriceShow": 95.00
    },
    {
      "IsStockLimit": true,
      "ProductId": 100014,
      "ProductType": 1,
      "ProductName": "保税仓：Merries花王婴儿纸尿裤S82片适用4-8kg   ",
      "ProductNamenext":"周年店庆",
      "Stock": 70,
      "PresellCount": 0,
      "LeaveStoreDay": 0,
      "ImgUrl": "./images/156629_01_01.jpg",
      "ShowImgUrl": "./images",
      "SaleState": true,
      "MarketPrice": 15.0000,
      "PromotionStock": 70,
      "PromotionUseStock": 0,
      "PromPrice": 690,
      "PromPriceShow": 79.00
    }]
}
